odoo/addons/contract_variable_qty_timesheet/README.rst
odoo/addons/contract_variable_qty_timesheet/__init__.py
odoo/addons/contract_variable_qty_timesheet/__manifest__.py
odoo/addons/contract_variable_qty_timesheet/data/contract_line_qty_formula_data.xml
odoo/addons/contract_variable_qty_timesheet/i18n/es.po
odoo/addons/contract_variable_qty_timesheet/static/description/icon.png
odoo11_addon_contract_variable_qty_timesheet-11.0.1.0.0.dist-info/DESCRIPTION.rst
odoo11_addon_contract_variable_qty_timesheet-11.0.1.0.0.dist-info/METADATA
odoo11_addon_contract_variable_qty_timesheet-11.0.1.0.0.dist-info/RECORD
odoo11_addon_contract_variable_qty_timesheet-11.0.1.0.0.dist-info/WHEEL
odoo11_addon_contract_variable_qty_timesheet-11.0.1.0.0.dist-info/metadata.json
odoo11_addon_contract_variable_qty_timesheet-11.0.1.0.0.dist-info/top_level.txt
